llm_linux_sdk/__init__.py
llm_linux_sdk/client/__init__.py
llm_linux_sdk/client/model_client.py
llm_linux_sdk/config/__init__.py
llm_linux_sdk/config/manager.py
llm_linux_sdk/config/setup.py
llm_linux_sdk/interface/__init__.py
llm_linux_sdk/interface/chat.py
llm_linux_sdk/utils/__init__.py
llm_linux_sdk/utils/license_validator.py
onemo_llm_sdk-0.1.1.dist-info/METADATA
onemo_llm_sdk-0.1.1.dist-info/WHEEL
onemo_llm_sdk-0.1.1.dist-info/top_level.txt
onemo_llm_sdk-0.1.1.dist-info/RECORD
